nukr/__init__.py
nukr/command.py
nukr/nuke_base.py
nukr/nuke_reddit.py
nukr-0.1.0a1.dist-info/WHEEL
nukr-0.1.0a1.dist-info/METADATA
nukr-0.1.0a1.dist-info/RECORD
