Metadata-Version: 2.1
Name: nukr
Version: 0.1.0a1
Summary: 
Author: 0
Requires-Python: >=3.9,<4.0
Classifier: Programming Language :: Python :: 3
Classifier: Programming Language :: Python :: 3.10
Classifier: Programming Language :: Python :: 3.9
Requires-Dist: click (>=8.0.3,<9.0.0)
Requires-Dist: click-sources (>=0.1.0-alpha.1,<0.2.0)
Requires-Dist: dateparser (>=1.1.0,<2.0.0)
Requires-Dist: praw (>=7.5.0,<8.0.0)
Requires-Dist: requests (>=2.26.0,<3.0.0)
